{
 "absolute_value": 0,
 "align_labels_right": 0,
 "creation": "2026-05-20 13:41:46.378382",
 "custom_format": 1,
 "default_print_language": "en",
 "disabled": 0,
 "doc_type": "Assessment Result",
 "docstatus": 0,
 "doctype": "Print Format",
 "font_size": 14,
 "html": "{% set student = frappe.get_doc(\"Student\", doc.student) if doc.student else None %}\n{% set student_group = frappe.get_doc(\"Student Group\", doc.student_group) if doc.student_group else None %}\n{% set group_instructor = student_group.instructors[0] if student_group and student_group.instructors else None %}\n{% set instructor = frappe.get_doc(\"Instructor\", group_instructor.instructor) if group_instructor and group_instructor.instructor else None %}\n\n{# Get only the latest passed attempt linked with this Assessment Result #}\n{% set quiz_activities = frappe.get_all(\n    \"Quiz Activity\",\n    filters={\n        \"custom_assesment_result\": doc.name,\n        \"status\": \"Pass\"\n    },\n    fields=[\n        \"name\",\n        \"student\",\n        \"custom_student_group\",\n        \"custom_assesment_plan\",\n        \"quiz\",\n        \"status\",\n        \"score\",\n        \"activity_date\",\n        \"creation\"\n    ],\n    order_by=\"activity_date desc, creation desc\",\n    limit_page_length=1\n) %}\n\n{# Fallback if Quiz Activity is not directly linked with Assessment Result #}\n{% if not quiz_activities %}\n    {% set quiz_activities = frappe.get_all(\n        \"Quiz Activity\",\n        filters={\n            \"student\": doc.student,\n            \"custom_student_group\": doc.student_group,\n            \"custom_assesment_plan\": doc.assessment_plan,\n            \"status\": \"Pass\"\n        },\n        fields=[\n            \"name\",\n            \"student\",\n            \"custom_student_group\",\n            \"custom_assesment_plan\",\n            \"quiz\",\n            \"status\",\n            \"score\",\n            \"activity_date\",\n            \"creation\"\n        ],\n        order_by=\"activity_date desc, creation desc\",\n        limit_page_length=1\n    ) %}\n{% endif %}\n\n<style>\n@page {\n    size: A4;\n    margin: 10mm 10mm 9mm;\n}\n\n.print-format {\n    font-family: Arial, Helvetica, sans-serif;\n    font-size: 10px;\n    color: #333;\n}\n\n.theory-page {\n    max-width: 190mm;\n    margin: 0 auto;\n}\n\n.theory-header {\n    display: table;\n    width: 100%;\n    margin-bottom: 8px;\n}\n\n.brand-left,\n.brand-right,\n.brand-title {\n    display: table-cell;\n    vertical-align: top;\n}\n\n.brand-left,\n.brand-right {\n    width: 23%;\n}\n\n.brand-right {\n    text-align: right;\n}\n\n.brand-mark {\n    color: #1f62ad;\n    font-size: 22px;\n    font-weight: 800;\n    line-height: 1;\n}\n\n.brand-sub {\n    color: #1f62ad;\n    font-size: 10px;\n    font-weight: 700;\n    margin-top: 2px;\n}\n\n.adnoc-front {\n    text-align: right;\n}\n\n.adnoc-front-img {\n    max-width: 66px;\n    max-height: 88px;\n    object-fit: contain;\n}\n\n.title-main {\n    margin-top: 22px;\n    font-size: 20px;\n    line-height: 1.1;\n    font-weight: 800;\n    color: #1f62ad;\n    white-space: normal;\n}\n\n.title-main .orange-text {\n    color: #eb7b3b;\n}\n\n.subtitle {\n    color: #1f62ad;\n    font-weight: 700;\n    margin: 5px 0 8px;\n    font-size: 12px;\n}\n\n.info-table,\n.assessment-table,\n.records-table,\n.sign-table {\n    width: 100%;\n    border-collapse: collapse;\n    table-layout: fixed;\n}\n\n.info-table td,\n.assessment-table td,\n.records-table td,\n.records-table th,\n.sign-table td,\n.sign-table th {\n    border: 1px solid #777;\n    vertical-align: middle;\n}\n\n.info-label {\n    background: #155fa8;\n    color: #fff;\n    font-weight: 700;\n    padding: 6px;\n    width: 20%;\n}\n\n.info-value {\n    padding: 5px 8px;\n    min-height: 18px;\n}\n\n.instruction {\n    margin: 7px 0;\n    font-size: 11px;\n}\n\n.unit-bar {\n    background: #eb7b3b;\n    color: #fff;\n    font-weight: 800;\n    padding: 5px 7px;\n    border: 1px solid #eb7b3b;\n}\n\n.unit-cell {\n    background: #155fa8;\n    color: #fff;\n    font-weight: 700;\n    width: 18%;\n    padding: 7px 6px;\n    line-height: 1.2;\n}\n\n.question-cell {\n    width: 31%;\n    padding: 7px;\n    line-height: 1.25;\n}\n\n.options-cell {\n    width: 51%;\n    padding: 6px 7px;\n}\n\n.option-row {\n    display: table;\n    width: 100%;\n    line-height: 1.25;\n    page-break-inside: avoid;\n}\n\n.option-text {\n    display: table-cell;\n    padding: 1px 5px 1px 0;\n}\n\n.box {\n    display: table-cell;\n    width: 15px;\n    color: #1f62ad;\n    font-size: 13px;\n    line-height: 1;\n    text-align: center;\n}\n\n.question-title {\n    font-weight: 700;\n    margin-bottom: 4px;\n}\n\n.result-note {\n    color: #c73636;\n    font-size: 9px;\n    margin-top: 4px;\n}\n\n.summary-title {\n    margin-top: 10px;\n}\n\n.records-table th,\n.sign-table th {\n    background: #eb7b3b;\n    color: #fff;\n    font-weight: 800;\n    padding: 6px;\n}\n\n.records-table td,\n.sign-table td {\n    padding: 6px;\n    height: 42px;\n}\n\n.signature-img {\n    max-width: 120px;\n    max-height: 38px;\n    object-fit: contain;\n}\n\n.declaration-section {\n    margin: 8px 0 6px;\n    font-size: 10px;\n    line-height: 1.25;\n}\n\n.declaration-section p {\n    margin: 2px 0;\n}\n\n.center {\n    text-align: center;\n}\n\n.footer-company {\n    margin-top: 7px;\n    text-align: right;\n    color: #1f62ad;\n    font-weight: 800;\n    border-top: 2px solid #1f62ad;\n    padding-top: 4px;\n}\n\n.avoid-break {\n    page-break-inside: avoid;\n}\n</style>\n\n<div class=\"theory-page\">\n\n    <div class=\"theory-header\">\n        <div class=\"brand-left\">\n            <div class=\"brand-mark\">\n                100%<br>HSE\n            </div>\n        </div>\n\n        <div class=\"brand-title\">\n            <div class=\"title-main\">\n                <span class=\"orange-text\">THEORY ASSESSMENT</span>\n                - {{ doc.course or \"ASSESSMENT\" }}\n            </div>\n        </div>\n\n        <div class=\"brand-right\">\n            <div class=\"adnoc-front\">\n                <img src=\"/files/adnoc.png\" class=\"adnoc-front-img\">\n            </div>\n        </div>\n    </div>\n\n    <div class=\"subtitle\">\n        {{ doc.course or doc.assessment_plan or \"Theory Assessment\" }} form\n    </div>\n\n    <table class=\"info-table\">\n        <tr>\n            <td class=\"info-label\">Candidate Name</td>\n\n            <td class=\"info-value\">\n                {{ doc.student_name or\n                   (student.student_name if student else \"\") or\n                   doc.student or \"\" }}\n            </td>\n\n            <td class=\"info-label\">Date</td>\n\n            <td class=\"info-value\">\n                {{ frappe.utils.formatdate(\n                    doc.course_start_date or\n                    doc.date or\n                    (student_group.from_date if student_group else None) or\n                    (student_group.custom_from_date if student_group else None)\n                ) }}\n            </td>\n        </tr>\n\n        <tr>\n            <td class=\"info-label\">Employing company</td>\n\n            <td class=\"info-value\">\n                {{ doc.customer_name or\n                   doc.custom_company or\n                   (student.custom_candidate_company_name if student else \"\") or\n                   (student.custom_student_company_name if student else \"\") or\n                   (student.customer_name if student else \"\") or\n                   (student_group.custom_customer if student_group else \"\") or\n                   \"\" }}\n            </td>\n\n            <td class=\"info-label\">Mobile number</td>\n\n            <td class=\"info-value\">\n                {% if student %}\n                    {{ student.student_mobile_number or student.custom_phone or \"\" }}\n                {% endif %}\n            </td>\n        </tr>\n\n        <tr>\n            <td class=\"info-label\">Student Group</td>\n\n            <td class=\"info-value\">\n                {{ doc.student_group or \"\" }}\n            </td>\n\n            <td class=\"info-label\">Result</td>\n\n            <td class=\"info-value\">\n                {% if quiz_activities %}\n                    {{ quiz_activities[0].status or \"\" }}\n                {% else %}\n                    {{ doc.grade or doc.total_score or \"\" }}\n                {% endif %}\n            </td>\n        </tr>\n    </table>\n\n    <div class=\"instruction\">\n        Use black biro pen to mark X in the correct box(s)\n    </div>\n\n    {% for activity in quiz_activities %}\n\n        {% set quiz_doc = frappe.get_doc(\"Quiz\", activity.quiz) if activity.quiz else None %}\n        {% set qa_doc = frappe.get_doc(\"Quiz Activity\", activity.name) %}\n\n        <div class=\"unit-bar\">\n            UNIT {{ loop.index }} -\n            {{ activity.quiz or doc.course or \"Theory Assessment\" }}\n        </div>\n\n        <table class=\"assessment-table\">\n\n            {% for result in qa_doc.result %}\n\n                {% set question_doc = frappe.get_doc(\n                    \"Question\",\n                    result.question\n                ) if result.question else None %}\n\n                <tr class=\"avoid-break\">\n\n                    {% if loop.first %}\n                        <td\n                            class=\"unit-cell\"\n                            rowspan=\"{{ qa_doc.result|length }}\"\n                        >\n                            {{ quiz_doc.title if quiz_doc else activity.quiz }}\n\n                            <br><br>\n\n                            Status: {{ activity.status or \"\" }}\n\n                            <br>\n\n                            Score: {{ activity.score or \"\" }}\n                        </td>\n                    {% endif %}\n\n                    <td class=\"question-cell\">\n                        <div class=\"question-title\">\n                            {{ frappe.utils.strip_html(\n                                question_doc.question\n                                if question_doc\n                                else result.question or \"\"\n                            ) }}\n                        </div>\n\n                        <div>\n                            Select the correct answer{% if question_doc and question_doc.question_type == \"Multiple Correct Answer\" %}(s){% endif %}\n                        </div>\n                    </td>\n\n                    <td class=\"options-cell\">\n\n                        {% if question_doc and question_doc.options %}\n\n                            {% for option in question_doc.options %}\n\n                                {% set option_text = frappe.utils.strip_html(\n                                    option.option or \"\"\n                                ) %}\n\n                                {% set selected =\n                                    (result.selected_option or \"\") == (option.option or \"\")\n                                    or\n                                    (result.selected_option or \"\") == option_text\n                                %}\n\n                                <div class=\"option-row\">\n                                    <span class=\"option-text\">\n                                        {{ option_text }}\n                                    </span>\n\n                                    <span class=\"box\">\n                                        {% if selected %}\n                                            \u2611\n                                        {% else %}\n                                            \u2610\n                                        {% endif %}\n                                    </span>\n                                </div>\n\n                            {% endfor %}\n\n                        {% else %}\n\n                            <div class=\"option-row\">\n                                <span class=\"option-text\">\n                                    {{ result.selected_option or \"\" }}\n                                </span>\n\n                                <span class=\"box\">\n                                    {% if result.selected_option %}\n                                        \u2611\n                                    {% else %}\n                                        \u2610\n                                    {% endif %}\n                                </span>\n                            </div>\n\n                        {% endif %}\n\n                        <div class=\"result-note\">\n                            Answer: {{ result.quiz_result or \"\" }}\n                        </div>\n\n                    </td>\n                </tr>\n\n            {% endfor %}\n\n        </table>\n\n    {% endfor %}\n\n    {% if not quiz_activities %}\n\n        <div class=\"unit-bar\">\n            ASSESSMENT QUESTIONS\n        </div>\n\n        <table class=\"assessment-table\">\n            <tr>\n                <td class=\"question-cell\">\n                    No passed Quiz Activity was found for this Assessment Result.\n                </td>\n\n                <td class=\"options-cell\">\n                    Please verify the Quiz Activity status and Assessment Result link.\n                </td>\n            </tr>\n        </table>\n\n    {% endif %}\n\n    <div class=\"unit-bar summary-title\">\n        CANDIDATE'S RECORDS\n    </div>\n\n    <table class=\"records-table\">\n        <tr>\n            <th>Quiz</th>\n            <th style=\"width:16%;\">Status</th>\n            <th style=\"width:16%;\">Score</th>\n            <th style=\"width:20%;\">Source of Evidence</th>\n        </tr>\n\n        {% if quiz_activities %}\n\n            {% set latest_activity = quiz_activities[0] %}\n\n            <tr>\n                <td>\n                    {{ latest_activity.quiz or \"\" }}\n                </td>\n\n                <td class=\"center\">\n                    {{ latest_activity.status or \"\" }}\n                </td>\n\n                <td class=\"center\">\n                    {{ latest_activity.score or \"\" }}\n                </td>\n\n                <td class=\"center\">\n                    Q\n                </td>\n            </tr>\n\n        {% else %}\n\n            <tr>\n                <td colspan=\"4\" class=\"center\">\n                    No passed attempt found\n                </td>\n            </tr>\n\n        {% endif %}\n    </table>\n\n    <p>\n        <b>Learner Name:</b>\n        {{ doc.student_name or\n           (student.student_name if student else \"\") or\n           doc.student or \"\" }}\n    </p>\n\n    <p>\n        <b>Training and Development Needs:</b>\n        {{ doc.comment or \"\" }}\n    </p>\n\n    <div class=\"declaration-section\">\n        <p>\n            Declaration: The person named was assessed by me against the\n            standards of performance specified in this document and in\n            accordance with the assessment guidance.\n        </p>\n\n        <p>\n            I consider that the above person has achieved a sufficient level\n            of understanding of the Light Vehicle Professional Driving Theory\n            course.\n        </p>\n\n        <p>\n            *I consider that the above person requires further training and\n            development in addition to that which is installation specific.\n        </p>\n    </div>\n\n    <table class=\"sign-table\">\n        <tr>\n            <th>Assessor's Name</th>\n            <th>Signature</th>\n            <th>Date</th>\n        </tr>\n\n        <tr>\n            <td>\n                {{ instructor.instructor_name\n                   if instructor\n                   else (\n                       group_instructor.instructor_name\n                       if group_instructor\n                       else frappe.session.user\n                   ) }}\n            </td>\n\n            <td class=\"center\">\n                {% if instructor and instructor.image %}\n                    <img\n                        src=\"{{ instructor.image }}\"\n                        class=\"signature-img\"\n                    >\n                {% endif %}\n            </td>\n\n            <td>\n                {{ frappe.utils.formatdate(\n                    doc.course_end_date or\n                    doc.course_start_date or\n                    doc.date\n                ) }}\n            </td>\n        </tr>\n    </table>\n\n    <div class=\"footer-company\">\n        Abu Dhabi National Oil Company\n    </div>\n\n</div>",
 "idx": 0,
 "line_breaks": 0,
 "margin_bottom": 15.0,
 "margin_left": 15.0,
 "margin_right": 15.0,
 "margin_top": 15.0,
 "modified": "2026-06-26 14:07:10.255886",
 "modified_by": "Administrator",
 "module": "Numerouno",
 "name": "Theory Assesment",
 "owner": "Administrator",
 "page_number": "Hide",
 "pdf_generator": "wkhtmltopdf",
 "print_designer": 0,
 "print_designer_template_app": "print_designer",
 "print_format_builder": 0,
 "print_format_builder_beta": 0,
 "print_format_for": "DocType",
 "print_format_type": "Jinja",
 "raw_printing": 0,
 "show_section_headings": 0,
 "standard": "Yes"
}