{
 "actions": [],
 "allow_rename": 1,
 "creation": "2026-05-06 21:46:54.353870",
 "doctype": "DocType",
 "editable_grid": 1,
 "engine": "InnoDB",
 "field_order": [
  "item",
  "description",
  "remarks",
  "action_by"
 ],
 "fields": [
  {
   "fieldname": "remarks",
   "fieldtype": "Text Editor",
   "in_filter": 1,
   "in_preview": 1,
   "in_standard_filter": 1,
   "label": "Remarks"
  },
  {
   "fieldname": "item",
   "fieldtype": "Data",
   "in_list_view": 1,
   "in_preview": 1,
   "in_standard_filter": 1,
   "label": "Item"
  },
  {
   "fieldname": "description",
   "fieldtype": "Text Editor",
   "in_list_view": 1,
   "in_preview": 1,
   "in_standard_filter": 1,
   "label": "Description"
  },
  {
   "fieldname": "action_by",
   "fieldtype": "Link",
   "in_list_view": 1,
   "in_preview": 1,
   "in_standard_filter": 1,
   "label": "Action By",
   "options": "User"
  }
 ],
 "grid_page_length": 50,
 "index_web_pages_for_search": 1,
 "istable": 1,
 "links": [],
 "modified": "2026-05-06 21:48:26.768646",
 "modified_by": "Administrator",
 "module": "Numerouno",
 "name": "Meeting Agenda Table",
 "owner": "Administrator",
 "permissions": [],
 "row_format": "Dynamic",
 "rows_threshold_for_grid_search": 20,
 "sort_field": "modified",
 "sort_order": "DESC",
 "states": []
}